Assignment 1/4to1multiplexer/multiplexer.v
module Mux4to1(i0, i1, i2, i3, s0, s1, out);
//s0 is the less significant bit of the control lines and s1 is the more significant bit

input i0, i1, i2, i3, s0, s1;
output wire out;
wire a1, a2, a3, a4;

assign a1 = (~s0) & (~s1) & i0;
assign a2 = (s0) & (~s1) & i1;
assign a3 = (~s0) & (s1) & i2;
assign a4 = (s0) & (s1) & i3;

assign out = a1 | a2 | a3 | a4;

endmodule

Assignment 1/4to1multiplexer/multiplexer_top.v
`include "multiplexer.v"

module multiplexer_top;

reg i0, i1, i2, i3, s0, s1;
wire out;

Mux4to1 uut(.i0(i0), .i1(i1), .i2(i2), .i3(i3), .s0(s0), .s1(s1), .out(out));

initial begin
    $dumpfile("multiplexer_tb.vcd");
    $dumpvars();
end

initial begin
    i0 = 0;
    #4;
    i0 = 1;
    #3;
    $finish;
end

initial begin
    i1 = 0;
    #4;
    i1 = 1;
    #3;
    $finish;
end

initial begin
    i2 = 0;
    #4;
    i2 = 1;
    #3;
    $finish;
end

initial begin
    i3 = 0;
    #4;
    i3 = 1;
    #3;
    $finish;
end

initial begin
    s1 = 0;
    forever #2 s1 = ~s1;
end

initial begin
    s0 = 0;
    forever #1 s0 = ~s0;
end

initial begin
    $monitor("time=%0d, s0=%b, s1=%b, i0=%b, i1=%b, i2=%b, i3=%b, out=%b", $time, s0, s1, i0, i1, i2, i3, out);
end

endmodule

Assignment 1/4to1multiplexer/multiplexer_tb.vcd
$date
	Mon Jan 16 00:24:01 2023
$end
$version
	Icarus Verilog
$end
$timescale
	1s
$end
$scope module multiplexer_top $end
$var wire 1 ! out $end
$var reg 1 " i0 $end
$var reg 1 # i1 $end
$var reg 1 $ i2 $end
$var reg 1 % i3 $end
$var reg 1 & s0 $end
$var reg 1 ' s1 $end
$scope module uut $end
$var wire 1 ( a1 $end
$var wire 1 ) a2 $end
$var wire 1 * a3 $end
$var wire 1 + a4 $end
$var wire 1 " i0 $end
$var wire 1 # i1 $end
$var wire 1 $ i2 $end
$var wire 1 % i3 $end
$var wire 1 ! out $end
$var wire 1 & s0 $end
$var wire 1 ' s1 $end
$upscope $end
$upscope $end
$enddefinitions $end
#0
$dumpvars
0+
0*
0)
0(
0'
0&
0%
0$
0#
0"
0!
$end
#1
1&
#2
0&
1'
#3
1&
#4
1(
1!
0+
0&
0'
1%
1$
1#
1"
#5
0(
1)
1&
#6
1*
0)
0&
1'
#7
0*
1+
1&
