Assignment 1/fulladder/full_adder.v
module fulladder(a, b, c_in, sum, c_out);

input a, b, c_in;
output sum, c_out;

wire x, y, z;

assign sum = a ^ b ^ c_in;

and a1(x, a, b);
and a2(y, a, c_in);
and a3(z, b, c_in);

or o2(c_out, x, y, z);

endmodule

Assignment 1/fulladder/full_adder_tb.v
`include "full_adder.v"

module full_adder_tb;

reg a, b, cin;
wire sum, cout;

fulladder foo(.a(a), .b(b), .c_in(cin), .c_out(cout), .sum(sum));

initial begin
    $dumpfile("full_adder_tb.vcd");
    $dumpvars();
end

initial begin
    a = 1;
    #4;
    a = 0;
    #3;
    $finish;
end

initial begin
    b = 1;
    forever #2 b = ~b;
end

initial begin
    cin = 1;
    forever #1 cin = ~cin;
end

initial begin
    $monitor("time=%0d, A=%b, B=%b, Cin=%b, Sum=%b, Cout=%b", $time, a, b, cin, sum, cout);
end

endmodule

Assignment 1/fulladder/full_adder_tb.vcd
$date
	Sat Jan 14 14:44:30 2023
$end
$version
	Icarus Verilog
$end
$timescale
	1s
$end
$scope module full_adder_tb $end
$var wire 1 ! sum $end
$var wire 1 " cout $end
$var reg 1 # a $end
$var reg 1 $ b $end
$var reg 1 % cin $end
$scope module foo $end
$var wire 1 # a $end
$var wire 1 $ b $end
$var wire 1 % c_in $end
$var wire 1 " c_out $end
$var wire 1 ! sum $end
$var wire 1 & x $end
$var wire 1 ' y $end
$var wire 1 ( z $end
$upscope $end
$upscope $end
$enddefinitions $end
#0
$dumpvars
1(
1'
1&
1%
1$
1#
1"
1!
$end
#1
0!
0'
0(
0%
#2
1'
0&
1%
0$
#3
0"
1!
0'
0%
#4
1"
0!
1(
1%
1$
0#
#5
0"
1!
0(
0%
#6
1%
0$
#7
0!
0%
