Assignment 1/fullsubtractor/fullsubtractor.v
module fullsubtractor(a, b, c, diff, B_out);
input a, b, c;
output diff, B_out;

wire diff, B_out;
wire a1, a2, xo1;

// assign diff = a ^ b ^ c;
xor x1(diff, a, b, c);

// assign a1 = (c & ~(a ^ b));
// assign a2 = (~a & b);
// assign B_out = a1 | a2;

xor x2(xo1, a, b);
and A1(a1, c, ~xo1);
and A2(a2, ~a, b);
or o1(B_out, a1, a2);

endmodule

Assignment 1/fullsubtractor/fullsubtractor_tb.v
`include "fullsubtractor.v"

module fullsubtractor_tb;

reg a, b, bin;
wire d, bout;

fullsubtractor foo(.a(a), .b(b), .c(bin), .B_out(bout), .diff(d));

initial begin
    $dumpfile("full_subtractor_tb.vcd");
    $dumpvars();
end

initial begin
    a = 1;
    #4;
    a = 0;
    #3;
    $finish;
end

initial begin
    b = 1;
    forever #2 b = ~b;
end

initial begin
    bin = 1;
    forever #1 bin = ~bin;
end

initial begin
    $monitor("time=%0d, A=%b, B=%b, Bin=%b, Diff=%b, Bout=%b", $time, a, b, bin, d, bout);
end

endmodule

Assignment 1/fullsubtractor/full_subtractor_tb.vcd
$date
	Mon Jan 16 16:02:51 2023
$end
$version
	Icarus Verilog
$end
$timescale
	1s
$end
$scope module fullsubtractor_tb $end
$var wire 1 ! d $end
$var wire 1 " bout $end
$var reg 1 # a $end
$var reg 1 $ b $end
$var reg 1 % bin $end
$scope module foo $end
$var wire 1 " B_out $end
$var wire 1 # a $end
$var wire 1 & a1 $end
$var wire 1 ' a2 $end
$var wire 1 $ b $end
$var wire 1 % c $end
$var wire 1 ! diff $end
$var wire 1 ( xo1 $end
$upscope $end
$upscope $end
$enddefinitions $end
#0
$dumpvars
0(
0'
1&
1%
1$
1#
1"
1!
$end
#1
0"
0!
0&
0%
#2
0"
0&
1(
1%
0$
#3
1!
0%
#4
1"
1'
0!
1%
1$
0#
#5
1!
0%
#6
1&
1"
0(
0'
1%
0$
#7
0"
0!
0&
0%
